cloudrail/terraform_0_12/__init__.py
cloudrail/terraform_0_12/terraform
cloudrail_terraform_0_12-0.36.0.dist-info/METADATA
cloudrail_terraform_0_12-0.36.0.dist-info/WHEEL
cloudrail_terraform_0_12-0.36.0.dist-info/top_level.txt
cloudrail_terraform_0_12-0.36.0.dist-info/RECORD
