Metadata-Version: 2.1
Name: cloudrail-terraform-0-12
Version: 0.36.0
Summary: CloudRail custom terraform binary 0.12
Home-page: UNKNOWN
Author: Indeni
License: UNKNOWN
Platform: UNKNOWN
Requires-Python: >=3.6, <4
